[
  {
    "id": "tap-race",
    "package": "@open-party-lab/game-tap-race",
    "repo": "https://github.com/Hartwich/open-party-game-tap-race.git",
    "defaultLocalPath": "local-games/tap-race",
    "alternateLocalPaths": [
      "local-games/open-party-game-tap-race",
      "../tap-race",
      "../open-party-game-tap-race"
    ]
  },
  {
    "id": "pantomime",
    "package": "@open-party-lab/game-pantomime",
    "repo": "https://github.com/Hartwich/pantomime.git",
    "defaultLocalPath": "local-games/pantomime",
    "alternateLocalPaths": [
      "../pantomime"
    ]
  }
]
